bqredis/__init__.py
bqredis/py.typed
bqredis-0.0.8.dist-info/METADATA
bqredis-0.0.8.dist-info/WHEEL
bqredis-0.0.8.dist-info/licenses/LICENSE
bqredis-0.0.8.dist-info/RECORD
