Metadata-Version: 2.4
Name: bqredis
Version: 0.0.8
Summary: A Redis-backed cache for BigQuery
Project-URL: source_archive, https://github.com/DelfinaCare/bqredis/archive/c0f1b45444e52120a97ddca8401f46061f5a4113.zip
Author-email: "Ali.Ebrahim" <ali@delfina.com>
License-Expression: MIT
License-File: LICENSE
Classifier: License :: OSI Approved :: MIT License
Classifier: Operating System :: OS Independent
Classifier: Programming Language :: Python :: 3
Requires-Python: >=3.11
Requires-Dist: google-cloud-bigquery-storage>=2.32.0
Requires-Dist: google-cloud-bigquery>=3.35.1
Requires-Dist: pyarrow>=18.1.0
Requires-Dist: redis>=5.2.1
Provides-Extra: dev
Requires-Dist: fakeredis>=2.30.3; extra == 'dev'
Requires-Dist: mypy>=1.11.2; extra == 'dev'
Requires-Dist: pyarrow-stubs>=20.0.0.20250716; extra == 'dev'
Requires-Dist: pytest>=8.4.1; extra == 'dev'
